Workbook

Sheet Dashboard
A1: SELLER PERFORMANCE DASHBOARD
A3: Start date | B3: =DATE(YEAR(TODAY()),MONTH(TODAY()),1) -> 46296 | D3: End date | E3: =TODAY() -> 46312
A5: Net revenue | C5: Estimated profit | E5: Units sold
A6: =SUMIFS(Sales!$L$2:$L$501,Sales!$A$2:$A$501,">="&$B$3,Sales!$A$2:$A$501,"<="&$E$3,Sales!$P$2:$P$501,"<>Cancelled") -> 0 | C6: =SUMIFS(Sales!$O$2:$O$501,Sales!$A$2:$A$501,">="&$B$3,Sales!$A$2:$A$501,"<="&$E$3,Sales!$P$2:$P$501,"<>Cancelled")-SUMIFS(Expenses!$D$2:$D$201,Expenses!$A$2:$A$201,">="&$B$3,Expenses!$A$2:$A$201,"<="&$E$3) -> 0 | E6: =SUMIFS(Sales!$E$2:$E$501,Sales!$A$2:$A$501,">="&$B$3,Sales!$A$2:$A$501,"<="&$E$3,Sales!$P$2:$P$501,"<>Cancelled") -> 0
A8: Order lines | C8: Operating expenses | E8: Products listed
A9: =COUNTIFS(Sales!$A$2:$A$501,">="&$B$3,Sales!$A$2:$A$501,"<="&$E$3,Sales!$B$2:$B$501,"<>",Sales!$P$2:$P$501,"<>Cancelled") -> 0 | C9: =SUMIFS(Expenses!$D$2:$D$201,Expenses!$A$2:$A$201,">="&$B$3,Expenses!$A$2:$A$201,"<="&$E$3) -> 0 | E9: =COUNTIF(Products!$B$2:$B$204,"?*") -> 3
A12: How to use
A13: 1. Add or edit products on the Products sheet. Platform fee is entered as a percentage (5% = 5%).
A14: 2. On Sales, enter Date, Order ID, SKU, Quantity, Discount, Shipping Charged, Refund, and Status. Formula columns calculate automatically.
A15: 3. Add non-product business expenses on the Expenses sheet. The dashboard subtracts these from estimated profit.
A16: 4. Change the Dashboard start/end dates to view another period. Make sure sales dates are real spreadsheet dates.
A17: 5. Returns/refunds and cancelled orders need careful handling; enter refund amounts and use the status field consistently. Validate against actual settlement reports.

Sheet Start Here
A1: POCKETAI STUDIO | SELLER PROFIT TRACKER
A3: Track multiple products, daily orders, fees, expenses and estimated profit in one workbook.
A5: 1 | B5: Products sheet | C5: Enter each product's SKU, name, unit cost and selling price. Add packaging cost per unit.
A6: 2 | B6: Sales sheet | C6: Record one row per order line. Enter date, order ID, SKU, quantity, discounts, shipping charged and platform/payment fees.
A7: 3 | B7: Expenses sheet | C7: Record business expenses such as advertising, subscriptions, returns or other operating costs.
A8: 4 | B8: Dashboard sheet | C8: Choose a start and end date to see revenue, estimated profit, orders and top products.
A9: 5 | B9: Important | C9: This is a planning estimate, not accounting or tax advice. Enter actual fees, refunds and costs. Verify formulas against your marketplace statements.
A12: Workbook compatibility | B12: Designed for Excel and compatible spreadsheet apps. Formulas recalculate when opened in a supported spreadsheet.

Sheet Products
A1: SKU | B1: Product Name | C1: Category | D1: Unit Cost (₹) | E1: Packaging Cost / Unit (₹) | F1: Selling Price (₹) | G1: Default Platform Fee % | H1: Notes
A2: SKU001 | B2: Handmade Candle | C2: Home & Decor | D2: 120 | E2: 12 | F2: 249 | G2: 0.05 | H2: Example only — replace with your own data
A3: SKU002 | B3: Cotton Tote Bag | C3: Accessories | D3: 150 | E3: 15 | F3: 299 | G3: 0.05 | H3: Example only — replace with your own data
A4: SKU003 | B4: Digital Template | C4: Digital | D4: 10 | E4: 0 | F4: 99 | G4: 0.03 | H4: Example only — replace with your own data
A5: =IF(B5="","","SKU"&TEXT(ROW()-1,"000"))
A6: =IF(B6="","","SKU"&TEXT(ROW()-1,"000"))
A7: =IF(B7="","","SKU"&TEXT(ROW()-1,"000"))
A8: =IF(B8="","","SKU"&TEXT(ROW()-1,"000"))
A9: =IF(B9="","","SKU"&TEXT(ROW()-1,"000"))
A10: =IF(B10="","","SKU"&TEXT(ROW()-1,"000"))
A11: =IF(B11="","","SKU"&TEXT(ROW()-1,"000"))
A12: =IF(B12="","","SKU"&TEXT(ROW()-1,"000"))
A13: =IF(B13="","","SKU"&TEXT(ROW()-1,"000"))
A14: =IF(B14="","","SKU"&TEXT(ROW()-1,"000"))
A15: =IF(B15="","","SKU"&TEXT(ROW()-1,"000"))
A16: =IF(B16="","","SKU"&TEXT(ROW()-1,"000"))
... A204: =IF(B204="","","SKU"&TEXT(ROW()-1,"000"))

Sheet Sales
A1: Date | B1: Order ID | C1: SKU | D1: Product Name | E1: Quantity | F1: Selling Price / Unit (₹) | G1: Discount (₹) | H1: Shipping Charged (₹) | I1: Platform/Payment Fee (₹) | J1: Refund (₹) | K1: Gross Sales (₹) | L1: Net Revenue (₹) | M1: Product Cost (₹) | N1: Packaging Cost (₹) | O1: Estimated Profit (₹) | P1: Order Status | Q1: Notes
D2: =IFERROR(VLOOKUP(C2,Products!$A$2:$G$204,2,FALSE),"") | F2: =IFERROR(VLOOKUP(C2,Products!$A$2:$G$204,6,FALSE),0) -> 0 | I2: =IF(OR(E2="",F2=""),0,MAX(0,(E2*F2-G2+H2)*IFERROR(VLOOKUP(C2,Products!$A$2:$G$204,7,FALSE),0))) -> 0 | K2: =IF(OR(E2="",F2=""),0,E2*F2) -> 0 | L2: =IF(E2="",0,K2-G2+H2-I2-J2) -> 0 | M2: =IFERROR(E2*VLOOKUP(C2,Products!$A$2:$G$204,4,FALSE),0) -> 0 | N2: =IFERROR(E2*VLOOKUP(C2,Products!$A$2:$G$204,5,FALSE),0) -> 0 | O2: =IF(E2="",0,L2-M2-N2) -> 0
D3: =IFERROR(VLOOKUP(C3,Products!$A$2:$G$204,2,FALSE),"") | F3: =IFERROR(VLOOKUP(C3,Products!$A$2:$G$204,6,FALSE),0) -> 0 | I3: =IF(OR(E3="",F3=""),0,MAX(0,(E3*F3-G3+H3)*IFERROR(VLOOKUP(C3,Products!$A$2:$G$204,7,FALSE),0))) -> 0 | K3: =IF(OR(E3="",F3=""),0,E3*F3) -> 0 | L3: =IF(E3="",0,K3-G3+H3-I3-J3) -> 0 | M3: =IFERROR(E3*VLOOKUP(C3,Products!$A$2:$G$204,4,FALSE),0) -> 0 | N3: =IFERROR(E3*VLOOKUP(C3,Products!$A$2:$G$204,5,FALSE),0) -> 0 | O3: =IF(E3="",0,L3-M3-N3) -> 0
D4: =IFERROR(VLOOKUP(C4,Products!$A$2:$G$204,2,FALSE),"") | F4: =IFERROR(VLOOKUP(C4,Products!$A$2:$G$204,6,FALSE),0) -> 0 | I4: =IF(OR(E4="",F4=""),0,MAX(0,(E4*F4-G4+H4)*IFERROR(VLOOKUP(C4,Products!$A$2:$G$204,7,FALSE),0))) -> 0 | K4: =IF(OR(E4="",F4=""),0,E4*F4) -> 0 | L4: =IF(E4="",0,K4-G4+H4-I4-J4) -> 0 | M4: =IFERROR(E4*VLOOKUP(C4,Products!$A$2:$G$204,4,FALSE),0) -> 0 | N4: =IFERROR(E4*VLOOKUP(C4,Products!$A$2:$G$204,5,FALSE),0) -> 0 | O4: =IF(E4="",0,L4-M4-N4) -> 0
D5: =IFERROR(VLOOKUP(C5,Products!$A$2:$G$204,2,FALSE),"") | F5: =IFERROR(VLOOKUP(C5,Products!$A$2:$G$204,6,FALSE),0) -> 0 | I5: =IF(OR(E5="",F5=""),0,MAX(0,(E5*F5-G5+H5)*IFERROR(VLOOKUP(C5,Products!$A$2:$G$204,7,FALSE),0))) -> 0 | K5: =IF(OR(E5="",F5=""),0,E5*F5) -> 0 | L5: =IF(E5="",0,K5-G5+H5-I5-J5) -> 0 | M5: =IFERROR(E5*VLOOKUP(C5,Products!$A$2:$G$204,4,FALSE),0) -> 0 | N5: =IFERROR(E5*VLOOKUP(C5,Products!$A$2:$G$204,5,FALSE),0) -> 0 | O5: =IF(E5="",0,L5-M5-N5) -> 0
D6: =IFERROR(VLOOKUP(C6,Products!$A$2:$G$204,2,FALSE),"") | F6: =IFERROR(VLOOKUP(C6,Products!$A$2:$G$204,6,FALSE),0) -> 0 | I6: =IF(OR(E6="",F6=""),0,MAX(0,(E6*F6-G6+H6)*IFERROR(VLOOKUP(C6,Products!$A$2:$G$204,7,FALSE),0))) -> 0 | K6: =IF(OR(E6="",F6=""),0,E6*F6) -> 0 | L6: =IF(E6="",0,K6-G6+H6-I6-J6) -> 0 | M6: =IFERROR(E6*VLOOKUP(C6,Products!$A$2:$G$204,4,FALSE),0) -> 0 | N6: =IFERROR(E6*VLOOKUP(C6,Products!$A$2:$G$204,5,FALSE),0) -> 0 | O6: =IF(E6="",0,L6-M6-N6) -> 0
D7: =IFERROR(VLOOKUP(C7,Products!$A$2:$G$204,2,FALSE),"") | F7: =IFERROR(VLOOKUP(C7,Products!$A$2:$G$204,6,FALSE),0) -> 0 | I7: =IF(OR(E7="",F7=""),0,MAX(0,(E7*F7-G7+H7)*IFERROR(VLOOKUP(C7,Products!$A$2:$G$204,7,FALSE),0))) -> 0 | K7: =IF(OR(E7="",F7=""),0,E7*F7) -> 0 | L7: =IF(E7="",0,K7-G7+H7-I7-J7) -> 0 | M7: =IFERROR(E7*VLOOKUP(C7,Products!$A$2:$G$204,4,FALSE),0) -> 0 | N7: =IFERROR(E7*VLOOKUP(C7,Products!$A$2:$G$204,5,FALSE),0) -> 0 | O7: =IF(E7="",0,L7-M7-N7) -> 0
D8: =IFERROR(VLOOKUP(C8,Products!$A$2:$G$204,2,FALSE),"") | F8: =IFERROR(VLOOKUP(C8,Products!$A$2:$G$204,6,FALSE),0) -> 0 | I8: =IF(OR(E8="",F8=""),0,MAX(0,(E8*F8-G8+H8)*IFERROR(VLOOKUP(C8,Products!$A$2:$G$204,7,FALSE),0))) -> 0 | K8: =IF(OR(E8="",F8=""),0,E8*F8) -> 0 | L8: =IF(E8="",0,K8-G8+H8-I8-J8) -> 0 | M8: =IFERROR(E8*VLOOKUP(C8,Products!$A$2:$G$204,4,FALSE),0) -> 0 | N8: =IFERROR(E8*VLOOKUP(C8,Products!$A$2:$G$204,5,FALSE),0) -> 0 | O8: =IF(E8="",0,L8-M8-N8) -> 0
D9: =IFERROR(VLOOKUP(C9,Products!$A$2:$G$204,2,FALSE),"") | F9: =IFERROR(VLOOKUP(C9,Products!$A$2:$G$204,6,FALSE),0) -> 0 | I9: =IF(OR(E9="",F9=""),0,MAX(0,(E9*F9-G9+H9)*IFERROR(VLOOKUP(C9,Products!$A$2:$G$204,7,FALSE),0))) -> 0 | K9: =IF(OR(E9="",F9=""),0,E9*F9) -> 0 | L9: =IF(E9="",0,K9-G9+H9-I9-J9) -> 0 | M9: =IFERROR(E9*VLOOKUP(C9,Products!$A$2:$G$204,4,FALSE),0) -> 0 | N9: =IFERROR(E9*VLOOKUP(C9,Products!$A$2:$G$204,5,FALSE),0) -> 0 | O9: =IF(E9="",0,L9-M9-N9) -> 0
D10: =IFERROR(VLOOKUP(C10,Products!$A$2:$G$204,2,FALSE),"") | F10: =IFERROR(VLOOKUP(C10,Products!$A$2:$G$204,6,FALSE),0) -> 0 | I10: =IF(OR(E10="",F10=""),0,MAX(0,(E10*F10-G10+H10)*IFERROR(VLOOKUP(C10,Products!$A$2:$G$204,7,FALSE),0))) -> 0 | K10: =IF(OR(E10="",F10=""),0,E10*F10) -> 0 | L10: =IF(E10="",0,K10-G10+H10-I10-J10) -> 0 | M10: =IFERROR(E10*VLOOKUP(C10,Products!$A$2:$G$204,4,FALSE),0) -> 0 | N10: =IFERROR(E10*VLOOKUP(C10,Products!$A$2:$G$204,5,FALSE),0) -> 0 | O10: =IF(E10="",0,L10-M10-N10) -> 0
D11: =IFERROR(VLOOKUP(C11,Products!$A$2:$G$204,2,FALSE),"") | F11: =IFERROR(VLOOKUP(C11,Products!$A$2:$G$204,6,FALSE),0) -> 0 | I11: =IF(OR(E11="",F11=""),0,MAX(0,(E11*F11-G11+H11)*IFERROR(VLOOKUP(C11,Products!$A$2:$G$204,7,FALSE),0))) -> 0 | K11: =IF(OR(E11="",F11=""),0,E11*F11) -> 0 | L11: =IF(E11="",0,K11-G11+H11-I11-J11) -> 0 | M11: =IFERROR(E11*VLOOKUP(C11,Products!$A$2:$G$204,4,FALSE),0) -> 0 | N11: =IFERROR(E11*VLOOKUP(C11,Products!$A$2:$G$204,5,FALSE),0) -> 0 | O11: =IF(E11="",0,L11-M11-N11) -> 0
D12: =IFERROR(VLOOKUP(C12,Products!$A$2:$G$204,2,FALSE),"") | F12: =IFERROR(VLOOKUP(C12,Products!$A$2:$G$204,6,FALSE),0) -> 0 | I12: =IF(OR(E12="",F12=""),0,MAX(0,(E12*F12-G12+H12)*IFERROR(VLOOKUP(C12,Products!$A$2:$G$204,7,FALSE),0))) -> 0 | K12: =IF(OR(E12="",F12=""),0,E12*F12) -> 0 | L12: =IF(E12="",0,K12-G12+H12-I12-J12) -> 0 | M12: =IFERROR(E12*VLOOKUP(C12,Products!$A$2:$G$204,4,FALSE),0) -> 0 | N12: =IFERROR(E12*VLOOKUP(C12,Products!$A$2:$G$204,5,FALSE),0) -> 0 | O12: =IF(E12="",0,L12-M12-N12) -> 0
D13: =IFERROR(VLOOKUP(C13,Products!$A$2:$G$204,2,FALSE),"") | F13: =IFERROR(VLOOKUP(C13,Products!$A$2:$G$204,6,FALSE),0) -> 0 | I13: =IF(OR(E13="",F13=""),0,MAX(0,(E13*F13-G13+H13)*IFERROR(VLOOKUP(C13,Products!$A$2:$G$204,7,FALSE),0))) -> 0 | K13: =IF(OR(E13="",F13=""),0,E13*F13) -> 0 | L13: =IF(E13="",0,K13-G13+H13-I13-J13) -> 0 | M13: =IFERROR(E13*VLOOKUP(C13,Products!$A$2:$G$204,4,FALSE),0) -> 0 | N13: =IFERROR(E13*VLOOKUP(C13,Products!$A$2:$G$204,5,FALSE),0) -> 0 | O13: =IF(E13="",0,L13-M13-N13) -> 0
... D501: =IFERROR(VLOOKUP(C501,Products!$A$2:$G$204,2,FALSE),"") | F501: =IFERROR(VLOOKUP(C501,Products!$A$2:$G$204,6,FALSE),0) -> 0 | I501: =IF(OR(E501="",F501=""),0,MAX(0,(E501*F501-G501+H501)*IFERROR(VLOOKUP(C501,Products!$A$2:$G$204,7,FALSE),0))) -> 0 | K501: =IF(OR(E501="",F501=""),0,E501*F501) -> 0 | L501: =IF(E501="",0,K501-G501+H501-I501-J501) -> 0 | M501: =IFERROR(E501*VLOOKUP(C501,Products!$A$2:$G$204,4,FALSE),0) -> 0 | N501: =IFERROR(E501*VLOOKUP(C501,Products!$A$2:$G$204,5,FALSE),0) -> 0 | O501: =IF(E501="",0,L501-M501-N501) -> 0

Sheet Expenses
A1: Date | B1: Expense Category | C1: Description | D1: Amount (₹) | E1: Payment Method | F1: Notes
